LICENSE.txt
MANIFEST.in
README.rst
setup.py
dlipower/__init__.py
dlipower/debug.py
dlipower/dlipower.py
dlipower/package_metadata.json
dlipower.egg-info/PKG-INFO
dlipower.egg-info/SOURCES.txt
dlipower.egg-info/dependency_links.txt
dlipower.egg-info/requires.txt
dlipower.egg-info/top_level.txt
dlipower.egg-info/zip-safe
scripts/dlipower
scripts/fence_dli
test/test_dlipower.py